Bakorder/__init__.py
Bakorder/main.py
bact_order-0.0.2.dist-info/METADATA
bact_order-0.0.2.dist-info/WHEEL
bact_order-0.0.2.dist-info/entry_points.txt
bact_order-0.0.2.dist-info/top_level.txt
bact_order-0.0.2.dist-info/RECORD
